source_infuser/__init__.py
source_infuser/ignore.py
source_infuser/logic.py
source_infuser/logs.py
source_infuser/scripts/__init__.py
source_infuser/scripts/infuser.py
source_infuser-0.0.3.dist-info/METADATA
source_infuser-0.0.3.dist-info/WHEEL
source_infuser-0.0.3.dist-info/entry_points.txt
source_infuser-0.0.3.dist-info/top_level.txt
source_infuser-0.0.3.dist-info/RECORD
