Metadata-Version: 2.1
Name: source-infuser
Version: 0.0.3
Summary: A package to prepare your software project for continuous infusion into your AI assistant
Home-page: https://github.com/ivanzhovannik/source-infuser
Author: Ivan Zhovannik
Author-email: i.zhovannik@maastrichtuniversity.nl
License: UNKNOWN
Platform: UNKNOWN
Classifier: Programming Language :: Python :: 3
Classifier: License :: OSI Approved :: MIT License
Classifier: Operating System :: OS Independent
Requires-Python: >=3.9
